PyApiManager/__init__.py
PyApiManager/apimanager.py
PyApiManager-0.0.8.dist-info/LICENSE
PyApiManager-0.0.8.dist-info/METADATA
PyApiManager-0.0.8.dist-info/WHEEL
PyApiManager-0.0.8.dist-info/top_level.txt
PyApiManager-0.0.8.dist-info/RECORD
