Metadata-Version: 2.1
Name: PyApiManager
Version: 0.0.8
Summary: This is a usefull api manager.
Home-page: https://github.com/pebbrian/PyApiManager
Author: Brian Pierre-Emmanuel & BESEVIC Ivan
Author-email: pebrian@outlook.fr
License: UNKNOWN
Platform: UNKNOWN
Classifier: Programming Language :: Python
Classifier: License :: OSI Approved :: MIT License
Requires-Dist: requests
